helios/__init__.py
helios/_version.py
helios/chkpt_migrator.py
helios/onnx.py
helios/py.typed
helios/trainer.py
helios/core/__init__.py
helios/core/cuda.py
helios/core/distributed.py
helios/core/logging.py
helios/core/rng.py
helios/core/utils.py
helios/data/__init__.py
helios/data/datamodule.py
helios/data/functional.py
helios/data/samplers.py
helios/data/transforms.py
helios/losses/__init__.py
helios/losses/utils.py
helios/losses/weighted_loss.py
helios/metrics/__init__.py
helios/metrics/functional.py
helios/metrics/metrics.py
helios/model/__init__.py
helios/model/model.py
helios/model/utils.py
helios/nn/__init__.py
helios/nn/swa_utils.py
helios/nn/utils.py
helios/nn/layers/__init__.py
helios/nn/layers/pool.py
helios/optim/__init__.py
helios/optim/utils.py
helios/plugins/__init__.py
helios/plugins/plugin.py
helios/plugins/optuna/__init__.py
helios/plugins/optuna/plugin.py
helios/plugins/optuna/utils.py
helios/scheduler/__init__.py
helios/scheduler/schedulers.py
helios/scheduler/utils.py
helios_ml-1.4.0.dist-info/licenses/LICENSE
helios_ml-1.4.0.dist-info/METADATA
helios_ml-1.4.0.dist-info/WHEEL
helios_ml-1.4.0.dist-info/top_level.txt
helios_ml-1.4.0.dist-info/RECORD
