Metadata-Version: 2.4
Name: helios-ml
Version: 1.4.0
Summary: A light-weight system for training AI networks using PyTorch
Author-email: "Mauricio A. Rovira Galvez" <maroviragalvez@outlook.com>
License-Expression: BSD-3-Clause
Project-URL: homepage, https://github.com/marovira/helios-ml
Project-URL: source, https://github.com/marovira/helios-ml
Project-URL: issues, https://github.com/marovira/helios-ml/issues
Project-URL: release notes, https://github.com/marovira/helios-ml/releases
Classifier: Intended Audience :: Science/Research
Classifier: Intended Audience :: Developers
Classifier: Topic :: Software Development
Classifier: Topic :: Scientific/Engineering :: Artificial Intelligence
Classifier: Programming Language :: Python :: 3
Classifier: Programming Language :: Python :: 3.11
Classifier: Programming Language :: Python :: 3.12
Classifier: Programming Language :: Python :: 3.13
Requires-Python: >=3.11
License-File: LICENSE
Requires-Dist: matplotlib>=3.9.2
Requires-Dist: numpy>=2.1.0
Requires-Dist: onnx>=1.16.0
Requires-Dist: onnxruntime>=1.19.0
Requires-Dist: opencv-python>=4.10.0.84
Requires-Dist: tensorboard>=2.17.0
Requires-Dist: torch>=2.5.0
Requires-Dist: torchvision>=0.20.0
Requires-Dist: tqdm>=4.66.0
Provides-Extra: tune
Requires-Dist: optuna>=4.0.0; extra == "tune"
Dynamic: license-file
